msgx/__init__.py
msgx/_version.py
msgx/asyncio.py
msgx/constants.py
msgx/context_manager.py
msgx/deserialise.py
msgx/msg_definitions.py
msgx/msgx.capnp
msgx/ndarray.capnp
msgx/receiver.py
msgx/context_manager/__init__.py
msgx/context_manager/info_label.py
msgx/context_manager/progress_bar.py
msgx/context_manager/types.py
msgx-1.0.3.dist-info/LICENSE
msgx-1.0.3.dist-info/METADATA
msgx-1.0.3.dist-info/WHEEL
msgx-1.0.3.dist-info/top_level.txt
msgx-1.0.3.dist-info/RECORD
