Metadata-Version: 2.1
Name: msgx
Version: 1.0.3
Summary: Message Exchange protocol.
Home-page: https://github.com/soraxas/msgx
Author: Tin Lai (@soraxas)
Author-email: oscar@tinyiu.com
License: MIT
Keywords: msgx deserialise c++ capnp protobuf zmq
Classifier: Intended Audience :: Developers
Classifier: Intended Audience :: End Users/Desktop
Classifier: Intended Audience :: System Administrators
Classifier: License :: OSI Approved :: MIT License
Classifier: Operating System :: MacOS
Classifier: Operating System :: POSIX
Classifier: Operating System :: Unix
Classifier: Programming Language :: Python :: 3.5
Classifier: Programming Language :: Python :: 3.6
Classifier: Programming Language :: Python :: 3.7
Classifier: Programming Language :: Python :: 3.8
Classifier: Programming Language :: Python :: 3.9
Classifier: Topic :: Desktop Environment
Classifier: Topic :: Terminals
Classifier: Topic :: Utilities
Requires-Python: >=3.5
License-File: LICENSE
Requires-Dist: pyzmq >=25.0
Requires-Dist: pycapnp >=1.1.0
Requires-Dist: numpy
